<root>
    <Level
        parDays="1"
        levelCompletionBonus="500"
        backgroundName="Level2"
        introText="Fashion FLESH and ENERGY into Street-Walkers to destroy your opponent's workshop."
        disableDiurnalCycle="true"
        playerName="Jack"
        playerBaseHealth="100">

        <GameDataOverride>
            <BaseLocations>
                <GameSize numPlayers="2">
                    <BaseLocation x="60" y="185"/>
                    <BaseLocation x="642" y="175"/>
                </GameSize>
            </BaseLocations>
        </GameDataOverride>

        <InitialResources>
            <Resource type="white" amount="60"/>
            <Resource type="blue" amount="20"/>
        </InitialResources>

        <AvailableUnits>
            <Unit type="grunt"/>
        </AvailableUnits>

        <AvailableSpells/>

        <Computer playerName="Ralph" baseHealth="15" team="1">
            <RepeatingDays>
                <Day repeatWaves="true">
                    <Wave delayBefore="15"><Unit type="grunt" count="1"/></Wave>
                    <Wave delayBefore="40"><Unit type="grunt" count="1"/></Wave>
                    <Wave delayBefore="25"/>
                </Day>
            </RepeatingDays>
        </Computer>

    </Level>

</root>
